Metadata-Version: 1.0
Name: distris-probability
Version: 0.2
Summary: Gaussian distributions
Home-page: UNKNOWN
Author: Azeez Liadi
Author-email: Liadiazeez3@gmail.com
License: UNKNOWN
Platform: UNKNOWN
